{
  "Angola Girassol": {
    "Unique": "Angola Girassol",
    "Exploration": "0",
    "Drilling": "0.330563353",
    "Production": "0.782785055",
    "Processing": "4.265456076",
    "Upgrading": "0",
    "Maintenance": "0",
    "Waste": "0",
    "Venting, Flaring, and Fugitive Emissions": "47.29067847",
    "Diluent": "0",
    "Miscellaneous": "2.909283516",
    "Transport to Refinery": "5.401430988",
    "Offsite emissions": "-0.731232733",
    "Net lifecycle emissions": "60.24896472",
    "API Gravity": "32",
    "Gas-to-Oil-Ratio": "633.4625",
    "Water-to-Oil-Ratio": "0.625",
    "Steam-to-Oil-Ratio": "0",
    "Flaring-to-Oil-Ratio": "27.36624332"
  },
  "Azerbaijan Azeri Light": {
    "Unique": "Azerbaijan Azeri Light",
    "Exploration": "0",
    "Drilling": "0.912880402",
    "Production": "8.412881663",
    "Processing": "5.91946957",
    "Upgrading": "0",
    "Maintenance": "0",
    "Waste": "0",
    "Venting, Flaring, and Fugitive Emissions": "49.40940592",
    "Diluent": "0",
    "Miscellaneous": "2.843918806",
    "Transport to Refinery": "6.780835884",
    "Offsite emissions": "-1.185172729",
    "Net lifecycle emissions": "73.09421952",
    "API Gravity": "35",
    "Gas-to-Oil-Ratio": "1299",
    "Water-to-Oil-Ratio": "1.800077252",
    "Steam-to-Oil-Ratio": "0",
    "Flaring-to-Oil-Ratio": "8.5"
  },
  "Nigeria Agbami": {
    "Unique": "Nigeria Agbami",
    "Exploration": "0",
    "Drilling": "1.172466674",
    "Production": "3.051531987",
    "Processing": "5.842940064",
    "Upgrading": "0",
    "Maintenance": "0",
    "Waste": "0",
    "Venting, Flaring, and Fugitive Emissions": "53.59718251",
    "Diluent": "0",
    "Miscellaneous": "2.729132766",
    "Transport to Refinery": "4.332724347",
    "Offsite emissions": "-0.089922389",
    "Net lifecycle emissions": "70.63605596",
    "API Gravity": "47",
    "Gas-to-Oil-Ratio": "1188.938",
    "Water-to-Oil-Ratio": "0",
    "Steam-to-Oil-Ratio": "0",
    "Flaring-to-Oil-Ratio": "47.6"
  },
  "Canada Hibernia": {
    "Unique": "Canada Hibernia",
    "Exploration": "0",
    "Drilling": "1.694442556",
    "Production": "11.29796524",
    "Processing": "9.661923755",
    "Upgrading": "0",
    "Maintenance": "0",
    "Waste": "0",
    "Venting, Flaring, and Fugitive Emissions": "63.48172341",
    "Diluent": "0",
    "Miscellaneous": "2.843918806",
    "Transport to Refinery": "2.105714624",
    "Offsite emissions": "1.554228245",
    "Net lifecycle emissions": "92.63991664",
    "API Gravity": "33.5",
    "Gas-to-Oil-Ratio": "2589.778185",
    "Water-to-Oil-Ratio": "1.460225841",
    "Steam-to-Oil-Ratio": "0",
    "Flaring-to-Oil-Ratio": "55.133936"
  },
  "Norway Ekofisk": {
    "Unique": "Norway Ekofisk",
    "Exploration": "0",
    "Drilling": "1.197381056",
    "Production": "13.5232604",
    "Processing": "7.99442761",
    "Upgrading": "0",
    "Maintenance": "0",
    "Waste": "0",
    "Venting, Flaring, and Fugitive Emissions": "56.63239553",
    "Diluent": "0",
    "Miscellaneous": "2.826414359",
    "Transport to Refinery": "3.234248002",
    "Offsite emissions": "-4.112710856",
    "Net lifecycle emissions": "81.2954161",
    "API Gravity": "36",
    "Gas-to-Oil-Ratio": "2957.725",
    "Water-to-Oil-Ratio": "0.215960867",
    "Steam-to-Oil-Ratio": "0",
    "Flaring-to-Oil-Ratio": "15.725"
  },
  "Norway Skarv": {
    "Unique": "Norway Skarv",
    "Exploration": "0",
    "Drilling": "1.491098192",
    "Production": "0",
    "Processing": "16.72051189",
    "Upgrading": "0",
    "Maintenance": "0",
    "Waste": "0",
    "Venting, Flaring, and Fugitive Emissions": "86.36090034",
    "Diluent": "0",
    "Miscellaneous": "2.791405463",
    "Transport to Refinery": "3.181187383",
    "Offsite emissions": "-6.833408733",
    "Net lifecycle emissions": "103.7116945",
    "API Gravity": "38.5",
    "Gas-to-Oil-Ratio": "5463",
    "Water-to-Oil-Ratio": "0.159202521",
    "Steam-to-Oil-Ratio": "0",
    "Flaring-to-Oil-Ratio": "76.56893478"
  },
  "Norway Oseberg": {
    "Unique": "Norway Oseberg",
    "Exploration": "0",
    "Drilling": "0.756141587",
    "Production": "11.75185202",
    "Processing": "5.691193774",
    "Upgrading": "0",
    "Maintenance": "0",
    "Waste": "0",
    "Venting, Flaring, and Fugitive Emissions": "47.94465844",
    "Diluent": "0",
    "Miscellaneous": "2.778332521",
    "Transport to Refinery": "3.743502866",
    "Offsite emissions": "22.85377343",
    "Net lifecycle emissions": "95.51945465",
    "API Gravity": "39.6",
    "Gas-to-Oil-Ratio": "1156.942295",
    "Water-to-Oil-Ratio": "0.2",
    "Steam-to-Oil-Ratio": "0",
    "Flaring-to-Oil-Ratio": "6.470315465"
  },
  "U.S. Bakken": {
    "Unique": "U.S. Bakken",
    "Exploration": "0",
    "Drilling": "4.21696123",
    "Production": "3.029694194",
    "Processing": "2.478510264",
    "Upgrading": "0",
    "Maintenance": "0",
    "Waste": "0",
    "Venting, Flaring, and Fugitive Emissions": "104.9657083",
    "Diluent": "0",
    "Miscellaneous": "2.804478405",
    "Transport to Refinery": "5.52533046",
    "Offsite emissions": "-1.779366855",
    "Net lifecycle emissions": "121.241316",
    "API Gravity": "41.9",
    "Gas-to-Oil-Ratio": "1273",
    "Water-to-Oil-Ratio": "0.9625",
    "Steam-to-Oil-Ratio": "0",
    "Flaring-to-Oil-Ratio": "443.3918548"
  },
  "U.S. California Midway Sunset": {
    "Unique": "U.S. California Midway Sunset",
    "Exploration": "0",
    "Drilling": "2.190943472",
    "Production": "5.083616699",
    "Processing": "2.571785548",
    "Upgrading": "0",
    "Maintenance": "0",
    "Waste": "0",
    "Venting, Flaring, and Fugitive Emissions": "40.23231922",
    "Diluent": "0",
    "Miscellaneous": "3.00544719",
    "Transport to Refinery": "4.023809831",
    "Offsite emissions": "14.50609836",
    "Net lifecycle emissions": "71.61402032",
    "API Gravity": "19",
    "Gas-to-Oil-Ratio": "39.92516004",
    "Water-to-Oil-Ratio": "4.176851275",
    "Steam-to-Oil-Ratio": "2.870996694",
    "Flaring-to-Oil-Ratio": "13.81002255"
  },
  "U.S. California South Belridge": {
    "Unique": "U.S. California South Belridge",
    "Exploration": "0",
    "Drilling": "7.921023097",
    "Production": "0.453396519",
    "Processing": "3.713383594",
    "Upgrading": "0",
    "Maintenance": "0",
    "Waste": "0",
    "Venting, Flaring, and Fugitive Emissions": "44.81383578",
    "Diluent": "0",
    "Miscellaneous": "3.118672162",
    "Transport to Refinery": "5.005180033",
    "Offsite emissions": "10.53566119",
    "Net lifecycle emissions": "75.56115238",
    "API Gravity": "23.7",
    "Gas-to-Oil-Ratio": "378.3535721",
    "Water-to-Oil-Ratio": "6.440179909",
    "Steam-to-Oil-Ratio": "2.594120104",
    "Flaring-to-Oil-Ratio": "1.907502125"
  },
  "U.S. California Wilmington": {
    "Unique": "U.S. California Wilmington",
    "Exploration": "0",
    "Drilling": "0.890707696",
    "Production": "18.31894611",
    "Processing": "3.097957027",
    "Upgrading": "0",
    "Maintenance": "0",
    "Waste": "0",
    "Venting, Flaring, and Fugitive Emissions": "41.04828156",
    "Diluent": "0",
    "Miscellaneous": "3.061948889",
    "Transport to Refinery": "0.071971843",
    "Offsite emissions": "5.340926472",
    "Net lifecycle emissions": "71.83073959",
    "API Gravity": "19.5",
    "Gas-to-Oil-Ratio": "219.4638342",
    "Water-to-Oil-Ratio": "18.9053979",
    "Steam-to-Oil-Ratio": "0.575303158",
    "Flaring-to-Oil-Ratio": "13.81002255"
  },
  "Brent 1996": {
    "Unique": "Brent 1996",
    "Exploration": "0",
    "Drilling": "0.757424053",
    "Production": "2.71053967",
    "Processing": "7.219746778",
    "Upgrading": "0",
    "Maintenance": "0",
    "Waste": "0",
    "Venting, Flaring, and Fugitive Emissions": "260.8765267",
    "Diluent": "0",
    "Miscellaneous": "2.804478405",
    "Transport to Refinery": "4.153456685",
    "Offsite emissions": "-2.084612337",
    "Net lifecycle emissions": "276.4375599",
    "API Gravity": "37.5",
    "Gas-to-Oil-Ratio": "3264.848965",
    "Water-to-Oil-Ratio": "1.713272684",
    "Steam-to-Oil-Ratio": "0",
    "Flaring-to-Oil-Ratio": "1668.949994"
  },
  "Kingfish 1996": {
    "Unique": "Kingfish 1996",
    "Exploration": "0",
    "Drilling": "0.630406006",
    "Production": "0.654411466",
    "Processing": "3.513677713",
    "Upgrading": "0",
    "Maintenance": "0",
    "Waste": "0",
    "Venting, Flaring, and Fugitive Emissions": "49.84013276",
    "Diluent": "0",
    "Miscellaneous": "2.735095456",
    "Transport to Refinery": "6.657191369",
    "Offsite emissions": "0.926116316",
    "Net lifecycle emissions": "64.95703109",
    "API Gravity": "47",
    "Gas-to-Oil-Ratio": "363",
    "Water-to-Oil-Ratio": "1.206761006",
    "Steam-to-Oil-Ratio": "0",
    "Flaring-to-Oil-Ratio": "62.55511683"
  },
  "Terra Nova 2015": {
    "Unique": "Terra Nova 2015",
    "Exploration": "0",
    "Drilling": "1.39825897",
    "Production": "15.63308057",
    "Processing": "5.914563024",
    "Upgrading": "0",
    "Maintenance": "0",
    "Waste": "0",
    "Venting, Flaring, and Fugitive Emissions": "72.60591169",
    "Diluent": "0",
    "Miscellaneous": "2.843918806",
    "Transport to Refinery": "2.22200447",
    "Offsite emissions": "-0.823513372",
    "Net lifecycle emissions": "99.79422416",
    "API Gravity": "35",
    "Gas-to-Oil-Ratio": "3650.653443",
    "Water-to-Oil-Ratio": "2.833501737",
    "Steam-to-Oil-Ratio": "0",
    "Flaring-to-Oil-Ratio": "133.3496149"
  },
  "Statfjord 1996": {
    "Unique": "Statfjord 1996",
    "Exploration": "0",
    "Drilling": "7.738831975",
    "Production": "3.225640042",
    "Processing": "4.805904089",
    "Upgrading": "0",
    "Maintenance": "0",
    "Waste": "0",
    "Venting, Flaring, and Fugitive Emissions": "50.97687256",
    "Diluent": "0",
    "Miscellaneous": "2.791405463",
    "Transport to Refinery": "3.838268366",
    "Offsite emissions": "1.4503628",
    "Net lifecycle emissions": "74.8272853",
    "API Gravity": "39",
    "Gas-to-Oil-Ratio": "840.8108468",
    "Water-to-Oil-Ratio": "0",
    "Steam-to-Oil-Ratio": "0",
    "Flaring-to-Oil-Ratio": "48.32488743"
  },
  "Gullfaks 2015": {
    "Unique": "Gullfaks 2015",
    "Exploration": "0",
    "Drilling": "0.489966693",
    "Production": "85.213681",
    "Processing": "10.37378605",
    "Upgrading": "0",
    "Maintenance": "0",
    "Waste": "0",
    "Venting, Flaring, and Fugitive Emissions": "70.01637367",
    "Diluent": "0",
    "Miscellaneous": "2.804478405",
    "Transport to Refinery": "3.872281564",
    "Offsite emissions": "114.9044972",
    "Net lifecycle emissions": "287.6750646",
    "API Gravity": "37.5",
    "Gas-to-Oil-Ratio": "2949.498362",
    "Water-to-Oil-Ratio": "9.444102946",
    "Steam-to-Oil-Ratio": "0",
    "Flaring-to-Oil-Ratio": "84.08835273"
  },
  "Asgard 2016": {
    "Unique": "Asgard 2016",
    "Exploration": "0",
    "Drilling": "9.28983431",
    "Production": "101.9070203",
    "Processing": "309.0379286",
    "Upgrading": "0",
    "Maintenance": "0",
    "Waste": "0",
    "Venting, Flaring, and Fugitive Emissions": "827.6071779",
    "Diluent": "0",
    "Miscellaneous": "2.697931955",
    "Transport to Refinery": "3.579611636",
    "Offsite emissions": "-134.2818831",
    "Net lifecycle emissions": "1119.837622",
    "API Gravity": "50.5",
    "Gas-to-Oil-Ratio": "110142.3003",
    "Water-to-Oil-Ratio": "1.433382153",
    "Steam-to-Oil-Ratio": "0",
    "Flaring-to-Oil-Ratio": "174.2657413"
  },
  "Draugen 1996": {
    "Unique": "Draugen 1996",
    "Exploration": "0",
    "Drilling": "7.34579379",
    "Production": "1.784595742",
    "Processing": "0.813130241",
    "Upgrading": "0",
    "Maintenance": "0",
    "Waste": "0",
    "Venting, Flaring, and Fugitive Emissions": "42.28232069",
    "Diluent": "0",
    "Miscellaneous": "2.778332521",
    "Transport to Refinery": "3.707227671",
    "Offsite emissions": "-0.30840322",
    "Net lifecycle emissions": "58.40299744",
    "API Gravity": "40",
    "Gas-to-Oil-Ratio": "304.0404859",
    "Water-to-Oil-Ratio": "0",
    "Steam-to-Oil-Ratio": "0",
    "Flaring-to-Oil-Ratio": "7.247604651"
  },
  "Grane 1996": {
    "Unique": "Grane 1996",
    "Exploration": "0",
    "Drilling": "7.825759363",
    "Production": "1.098877229",
    "Processing": "0.048851199",
    "Upgrading": "0",
    "Maintenance": "0",
    "Waste": "0",
    "Venting, Flaring, and Fugitive Emissions": "46.87946075",
    "Diluent": "0",
    "Miscellaneous": "2.992152673",
    "Transport to Refinery": "4.096939464",
    "Offsite emissions": "0.210227086",
    "Net lifecycle emissions": "63.15226777",
    "API Gravity": "23.7",
    "Gas-to-Oil-Ratio": "90.89302638",
    "Water-to-Oil-Ratio": "0.040391318",
    "Steam-to-Oil-Ratio": "0",
    "Flaring-to-Oil-Ratio": "68.76973881"
  },
  "Gudrun 2016": {
    "Unique": "Gudrun 2016",
    "Exploration": "0",
    "Drilling": "10.00817356",
    "Production": "3.257016154",
    "Processing": "9.762718935",
    "Upgrading": "0",
    "Maintenance": "0",
    "Waste": "0",
    "Venting, Flaring, and Fugitive Emissions": "56.85572725",
    "Diluent": "0",
    "Miscellaneous": "2.791405463",
    "Transport to Refinery": "3.777267428",
    "Offsite emissions": "-3.066929407",
    "Net lifecycle emissions": "83.38537938",
    "API Gravity": "30",
    "Gas-to-Oil-Ratio": "2652.673546",
    "Water-to-Oil-Ratio": "0.027971116",
    "Steam-to-Oil-Ratio": "0",
    "Flaring-to-Oil-Ratio": "11.52879542"
  },
  "Heidrun 1996": {
    "Unique": "Heidrun 1996",
    "Exploration": "0",
    "Drilling": "7.771144227",
    "Production": "2.13440907",
    "Processing": "4.203947587",
    "Upgrading": "0",
    "Maintenance": "0",
    "Waste": "0",
    "Venting, Flaring, and Fugitive Emissions": "43.8556694",
    "Diluent": "0",
    "Miscellaneous": "2.791405463",
    "Transport to Refinery": "3.777267428",
    "Offsite emissions": "-0.623719728",
    "Net lifecycle emissions": "63.91012345",
    "API Gravity": "30",
    "Gas-to-Oil-Ratio": "653.9798839",
    "Water-to-Oil-Ratio": "0",
    "Steam-to-Oil-Ratio": "0",
    "Flaring-to-Oil-Ratio": "15.36810719"
  },
  "Njord 2016": {
    "Unique": "Njord 2016",
    "Exploration": "0",
    "Drilling": "7.683742491",
    "Production": "30.97279213",
    "Processing": "68.41362644",
    "Upgrading": "0",
    "Maintenance": "0",
    "Waste": "0",
    "Venting, Flaring, and Fugitive Emissions": "202.5325997",
    "Diluent": "0",
    "Miscellaneous": "2.735095456",
    "Transport to Refinery": "3.628920107",
    "Offsite emissions": "-22.73625017",
    "Net lifecycle emissions": "293.2305261",
    "API Gravity": "46.6",
    "Gas-to-Oil-Ratio": "22560.92593",
    "Water-to-Oil-Ratio": "0.243684809",
    "Steam-to-Oil-Ratio": "0",
    "Flaring-to-Oil-Ratio": "18.37032281"
  },
  "Norne 2016": {
    "Unique": "Norne 2016",
    "Exploration": "0",
    "Drilling": "8.161172676",
    "Production": "45.75621212",
    "Processing": "8.681308959",
    "Upgrading": "0",
    "Maintenance": "0",
    "Waste": "0",
    "Venting, Flaring, and Fugitive Emissions": "62.38181572",
    "Diluent": "0",
    "Miscellaneous": "2.87006469",
    "Transport to Refinery": "3.870988993",
    "Offsite emissions": "-2.05826449",
    "Net lifecycle emissions": "129.6632987",
    "API Gravity": "32.7",
    "Gas-to-Oil-Ratio": "2198.142503",
    "Water-to-Oil-Ratio": "17.04491689",
    "Steam-to-Oil-Ratio": "0",
    "Flaring-to-Oil-Ratio": "62.77330047"
  },
  "Troll 1996": {
    "Unique": "Troll 1996",
    "Exploration": "0",
    "Drilling": "0.357280364",
    "Production": "1.153085634",
    "Processing": "12.79070192",
    "Upgrading": "0",
    "Maintenance": "0",
    "Waste": "0",
    "Venting, Flaring, and Fugitive Emissions": "63.98226844",
    "Diluent": "0",
    "Miscellaneous": "2.826414359",
    "Transport to Refinery": "3.795052447",
    "Offsite emissions": "-5.534519133",
    "Net lifecycle emissions": "79.37028403",
    "API Gravity": "35.9",
    "Gas-to-Oil-Ratio": "3578.589022",
    "Water-to-Oil-Ratio": "0",
    "Steam-to-Oil-Ratio": "0",
    "Flaring-to-Oil-Ratio": "0"
  },
  "Valhall 1996": {
    "Unique": "Valhall 1996",
    "Exploration": "0",
    "Drilling": "7.636817223",
    "Production": "0.935836077",
    "Processing": "6.080352791",
    "Upgrading": "0",
    "Maintenance": "0",
    "Waste": "0",
    "Venting, Flaring, and Fugitive Emissions": "49.79384709",
    "Diluent": "0",
    "Miscellaneous": "2.826414359",
    "Transport to Refinery": "3.795758481",
    "Offsite emissions": "-1.663543134",
    "Net lifecycle emissions": "69.40548289",
    "API Gravity": "36",
    "Gas-to-Oil-Ratio": "1224.724464",
    "Water-to-Oil-Ratio": "0.043374808",
    "Steam-to-Oil-Ratio": "0",
    "Flaring-to-Oil-Ratio": "15.60138431"
  },
  "UK Forties Blend": {
    "Unique": "UK Forties Blend",
    "Exploration": "0",
    "Drilling": "0.622870997",
    "Production": "21.56424301",
    "Processing": "0.388743445",
    "Upgrading": "0",
    "Maintenance": "0",
    "Waste": "0",
    "Venting, Flaring, and Fugitive Emissions": "24.53899548",
    "Diluent": "0",
    "Miscellaneous": "2.791405463",
    "Transport to Refinery": "3.186934032",
    "Offsite emissions": "2.992252232",
    "Net lifecycle emissions": "56.08544466",
    "API Gravity": "35",
    "Gas-to-Oil-Ratio": "269.04",
    "Water-to-Oil-Ratio": "8.7",
    "Steam-to-Oil-Ratio": "3",
    "Flaring-to-Oil-Ratio": "102.8330831"
  }
}
