{
  "Angola Girassol": {
    "Unique": "Angola Girassol",
    "Exploration": "0",
    "Drilling": "0.330563353",
    "Production": "0.915855629",
    "Processing": "4.336244069",
    "Upgrading": "0",
    "Maintenance": "0",
    "Waste": "0",
    "Venting, Flaring, and Fugitive Emissions": "44.37127596",
    "Diluent": "0",
    "Miscellaneous": "2.909283516",
    "Transport to Refinery": "5.401430988",
    "Offsite emissions": "-0.767441482",
    "Net lifecycle emissions": "57.49721203",
    "API Gravity": "32",
    "Gas-to-Oil-Ratio": "637.245",
    "Water-to-Oil-Ratio": "0.75",
    "Steam-to-Oil-Ratio": "0",
    "Flaring-to-Oil-Ratio": "3.219558038"
  },
  "Azerbaijan Azeri Light": {
    "Unique": "Azerbaijan Azeri Light",
    "Exploration": "0",
    "Drilling": "0.912880402",
    "Production": "10.17653407",
    "Processing": "5.938667364",
    "Upgrading": "0",
    "Maintenance": "0",
    "Waste": "0",
    "Venting, Flaring, and Fugitive Emissions": "48.51116592",
    "Diluent": "0",
    "Miscellaneous": "2.843918806",
    "Transport to Refinery": "6.780835884",
    "Offsite emissions": "-1.141200198",
    "Net lifecycle emissions": "74.02280225",
    "API Gravity": "35",
    "Gas-to-Oil-Ratio": "1299",
    "Water-to-Oil-Ratio": "2.160092703",
    "Steam-to-Oil-Ratio": "0",
    "Flaring-to-Oil-Ratio": "1"
  },
  "Nigeria Agbami": {
    "Unique": "Nigeria Agbami",
    "Exploration": "0",
    "Drilling": "1.172466674",
    "Production": "3.166750798",
    "Processing": "5.961829787",
    "Upgrading": "0",
    "Maintenance": "0",
    "Waste": "0",
    "Venting, Flaring, and Fugitive Emissions": "48.54078359",
    "Diluent": "0",
    "Miscellaneous": "2.729132766",
    "Transport to Refinery": "4.332724347",
    "Offsite emissions": "-0.106748301",
    "Net lifecycle emissions": "65.79693966",
    "API Gravity": "47",
    "Gas-to-Oil-Ratio": "1188.938",
    "Water-to-Oil-Ratio": "0",
    "Steam-to-Oil-Ratio": "0",
    "Flaring-to-Oil-Ratio": "5.6"
  },
  "Canada Hibernia": {
    "Unique": "Canada Hibernia",
    "Exploration": "0",
    "Drilling": "1.694442556",
    "Production": "8.598666186",
    "Processing": "6.334792707",
    "Upgrading": "0",
    "Maintenance": "0",
    "Waste": "0",
    "Venting, Flaring, and Fugitive Emissions": "48.77321551",
    "Diluent": "0",
    "Miscellaneous": "2.843918806",
    "Transport to Refinery": "2.105714624",
    "Offsite emissions": "1.525431494",
    "Net lifecycle emissions": "71.87618188",
    "API Gravity": "33.5",
    "Gas-to-Oil-Ratio": "1353.68965",
    "Water-to-Oil-Ratio": "0.950645282",
    "Steam-to-Oil-Ratio": "0",
    "Flaring-to-Oil-Ratio": "3.705678448"
  },
  "Norway Ekofisk": {
    "Unique": "Norway Ekofisk",
    "Exploration": "0",
    "Drilling": "1.197381056",
    "Production": "12.82875886",
    "Processing": "4.63356678",
    "Upgrading": "0",
    "Maintenance": "0",
    "Waste": "0",
    "Venting, Flaring, and Fugitive Emissions": "45.02496211",
    "Diluent": "0",
    "Miscellaneous": "2.826414359",
    "Transport to Refinery": "3.234248002",
    "Offsite emissions": "-1.476635606",
    "Net lifecycle emissions": "68.26869556",
    "API Gravity": "36",
    "Gas-to-Oil-Ratio": "1089.078",
    "Water-to-Oil-Ratio": "0.783524057",
    "Steam-to-Oil-Ratio": "0",
    "Flaring-to-Oil-Ratio": "0.65045416"
  },
  "Norway Skarv": {
    "Unique": "Norway Skarv",
    "Exploration": "0",
    "Drilling": "1.491098192",
    "Production": "0",
    "Processing": "16.8972686",
    "Upgrading": "0",
    "Maintenance": "0",
    "Waste": "0",
    "Venting, Flaring, and Fugitive Emissions": "78.30717349",
    "Diluent": "0",
    "Miscellaneous": "2.791405463",
    "Transport to Refinery": "3.181187383",
    "Offsite emissions": "-6.923678355",
    "Net lifecycle emissions": "95.74445477",
    "API Gravity": "38.5",
    "Gas-to-Oil-Ratio": "5463",
    "Water-to-Oil-Ratio": "0.191043025",
    "Steam-to-Oil-Ratio": "0",
    "Flaring-to-Oil-Ratio": "9.008109974"
  },
  "Norway Oseberg": {
    "Unique": "Norway Oseberg",
    "Exploration": "0",
    "Drilling": "0.756141587",
    "Production": "31.55938386",
    "Processing": "10.78958448",
    "Upgrading": "0",
    "Maintenance": "0",
    "Waste": "0",
    "Venting, Flaring, and Fugitive Emissions": "60.43557963",
    "Diluent": "0",
    "Miscellaneous": "2.778332521",
    "Transport to Refinery": "3.743502866",
    "Offsite emissions": "67.63805795",
    "Net lifecycle emissions": "177.7005829",
    "API Gravity": "39.6",
    "Gas-to-Oil-Ratio": "3021.743969",
    "Water-to-Oil-Ratio": "0.671210708",
    "Steam-to-Oil-Ratio": "0",
    "Flaring-to-Oil-Ratio": "1.643461822"
  },
  "U.S. Bakken": {
    "Unique": "U.S. Bakken",
    "Exploration": "0",
    "Drilling": "4.21696123",
    "Production": "3.377035733",
    "Processing": "3.108242495",
    "Upgrading": "0",
    "Maintenance": "0",
    "Waste": "0",
    "Venting, Flaring, and Fugitive Emissions": "52.61690564",
    "Diluent": "0",
    "Miscellaneous": "2.804478405",
    "Transport to Refinery": "5.52533046",
    "Offsite emissions": "-2.825552239",
    "Net lifecycle emissions": "68.82340172",
    "API Gravity": "41.9",
    "Gas-to-Oil-Ratio": "1273",
    "Water-to-Oil-Ratio": "1.155",
    "Steam-to-Oil-Ratio": "0",
    "Flaring-to-Oil-Ratio": "52.16374762"
  },
  "U.S. California Midway Sunset": {
    "Unique": "U.S. California Midway Sunset",
    "Exploration": "0",
    "Drilling": "2.190943472",
    "Production": "8.887727767",
    "Processing": "2.650254722",
    "Upgrading": "0",
    "Maintenance": "0",
    "Waste": "0",
    "Venting, Flaring, and Fugitive Emissions": "40.0855548",
    "Diluent": "0",
    "Miscellaneous": "3.00544719",
    "Transport to Refinery": "4.023809831",
    "Offsite emissions": "21.43420217",
    "Net lifecycle emissions": "82.27793995",
    "API Gravity": "19",
    "Gas-to-Oil-Ratio": "57.77498966",
    "Water-to-Oil-Ratio": "8.017289973",
    "Steam-to-Oil-Ratio": "4.292456995",
    "Flaring-to-Oil-Ratio": "1.624708535"
  },
  "U.S. California South Belridge": {
    "Unique": "U.S. California South Belridge",
    "Exploration": "0",
    "Drilling": "7.921023097",
    "Production": "0.935530468",
    "Processing": "3.818666093",
    "Upgrading": "0",
    "Maintenance": "0",
    "Waste": "0",
    "Venting, Flaring, and Fugitive Emissions": "45.95786084",
    "Diluent": "0",
    "Miscellaneous": "3.118672162",
    "Transport to Refinery": "5.005180033",
    "Offsite emissions": "7.263122804",
    "Net lifecycle emissions": "74.0200555",
    "API Gravity": "23.7",
    "Gas-to-Oil-Ratio": "395.8089851",
    "Water-to-Oil-Ratio": "15.67814884",
    "Steam-to-Oil-Ratio": "1.968306324",
    "Flaring-to-Oil-Ratio": "0.224412015"
  },
  "U.S. California Wilmington": {
    "Unique": "U.S. California Wilmington",
    "Exploration": "0",
    "Drilling": "0.890707696",
    "Production": "50.2043126",
    "Processing": "3.287934591",
    "Upgrading": "0",
    "Maintenance": "0",
    "Waste": "0",
    "Venting, Flaring, and Fugitive Emissions": "40.28186766",
    "Diluent": "0",
    "Miscellaneous": "3.061948889",
    "Transport to Refinery": "0.071971843",
    "Offsite emissions": "9.265536764",
    "Net lifecycle emissions": "107.06428",
    "API Gravity": "19.5",
    "Gas-to-Oil-Ratio": "278.6610386",
    "Water-to-Oil-Ratio": "42.93682722",
    "Steam-to-Oil-Ratio": "0.32377839",
    "Flaring-to-Oil-Ratio": "1.624708535"
  },
  "Brent 2006": {
    "Unique": "Brent 2006",
    "Exploration": "0",
    "Drilling": "0.757424053",
    "Production": "1.069871319",
    "Processing": "87.91970114",
    "Upgrading": "0",
    "Maintenance": "0",
    "Waste": "0",
    "Venting, Flaring, and Fugitive Emissions": "265.2799854",
    "Diluent": "0",
    "Miscellaneous": "2.804478405",
    "Transport to Refinery": "4.153456685",
    "Offsite emissions": "-45.1729846",
    "Net lifecycle emissions": "316.8119324",
    "API Gravity": "37.5",
    "Gas-to-Oil-Ratio": "28923.26928",
    "Water-to-Oil-Ratio": "28.12826535",
    "Steam-to-Oil-Ratio": "0",
    "Flaring-to-Oil-Ratio": "196.3470581"
  },
  "Kingfish 1998": {
    "Unique": "Kingfish 1998",
    "Exploration": "0",
    "Drilling": "0.630406006",
    "Production": "0.812889166",
    "Processing": "3.686586627",
    "Upgrading": "0",
    "Maintenance": "0",
    "Waste": "0",
    "Venting, Flaring, and Fugitive Emissions": "43.35354559",
    "Diluent": "0",
    "Miscellaneous": "2.735095456",
    "Transport to Refinery": "6.657191369",
    "Offsite emissions": "0.975156155",
    "Net lifecycle emissions": "58.85087037",
    "API Gravity": "47",
    "Gas-to-Oil-Ratio": "363",
    "Water-to-Oil-Ratio": "1.45754717",
    "Steam-to-Oil-Ratio": "0",
    "Flaring-to-Oil-Ratio": "7.359425509"
  },
  "Terra Nova 2006": {
    "Unique": "Terra Nova 2006",
    "Exploration": "0",
    "Drilling": "1.39825897",
    "Production": "3.127077216",
    "Processing": "3.51648305",
    "Upgrading": "0",
    "Maintenance": "0",
    "Waste": "0",
    "Venting, Flaring, and Fugitive Emissions": "46.47263028",
    "Diluent": "0",
    "Miscellaneous": "2.843918806",
    "Transport to Refinery": "2.22200447",
    "Offsite emissions": "-0.221444875",
    "Net lifecycle emissions": "59.35892792",
    "API Gravity": "35",
    "Gas-to-Oil-Ratio": "984.5399863",
    "Water-to-Oil-Ratio": "0.763185023",
    "Steam-to-Oil-Ratio": "0",
    "Flaring-to-Oil-Ratio": "21.90285946"
  },
  "Statfjord 2006": {
    "Unique": "Statfjord 2006",
    "Exploration": "0",
    "Drilling": "7.738831975",
    "Production": "63.20050929",
    "Processing": "9.647680969",
    "Upgrading": "0",
    "Maintenance": "0",
    "Waste": "0",
    "Venting, Flaring, and Fugitive Emissions": "58.43965531",
    "Diluent": "0",
    "Miscellaneous": "2.791405463",
    "Transport to Refinery": "3.838268366",
    "Offsite emissions": "1.462424858",
    "Net lifecycle emissions": "147.1187762",
    "API Gravity": "39",
    "Gas-to-Oil-Ratio": "2567.591543",
    "Water-to-Oil-Ratio": "11.12090097",
    "Steam-to-Oil-Ratio": "0",
    "Flaring-to-Oil-Ratio": "8.242174741"
  },
  "Gullfaks 2015": {
    "Unique": "Gullfaks 2015",
    "Exploration": "0",
    "Drilling": "0.489966693",
    "Production": "96.80197306",
    "Processing": "10.57427724",
    "Upgrading": "0",
    "Maintenance": "0",
    "Waste": "0",
    "Venting, Flaring, and Fugitive Emissions": "61.171542",
    "Diluent": "0",
    "Miscellaneous": "2.804478405",
    "Transport to Refinery": "3.872281564",
    "Offsite emissions": "115.893914",
    "Net lifecycle emissions": "291.6084329",
    "API Gravity": "37.5",
    "Gas-to-Oil-Ratio": "2949.498362",
    "Water-to-Oil-Ratio": "11.33292353",
    "Steam-to-Oil-Ratio": "0",
    "Flaring-to-Oil-Ratio": "9.89274738"
  },
  "Asgard 2016": {
    "Unique": "Asgard 2016",
    "Exploration": "0",
    "Drilling": "9.28983431",
    "Production": "102.6621134",
    "Processing": "309.4365811",
    "Upgrading": "0",
    "Maintenance": "0",
    "Waste": "0",
    "Venting, Flaring, and Fugitive Emissions": "809.3071091",
    "Diluent": "0",
    "Miscellaneous": "2.697931955",
    "Transport to Refinery": "3.579611636",
    "Offsite emissions": "-134.4584594",
    "Net lifecycle emissions": "1102.514722",
    "API Gravity": "50.5",
    "Gas-to-Oil-Ratio": "110142.3003",
    "Water-to-Oil-Ratio": "1.720058583",
    "Steam-to-Oil-Ratio": "0",
    "Flaring-to-Oil-Ratio": "20.50185191"
  },
  "Draugen 2006": {
    "Unique": "Draugen 2006",
    "Exploration": "0",
    "Drilling": "7.34579379",
    "Production": "5.492638253",
    "Processing": "0.929868779",
    "Upgrading": "0",
    "Maintenance": "0",
    "Waste": "0",
    "Venting, Flaring, and Fugitive Emissions": "41.71023699",
    "Diluent": "0",
    "Miscellaneous": "2.778332521",
    "Transport to Refinery": "3.707227671",
    "Offsite emissions": "-0.2663118",
    "Net lifecycle emissions": "61.69778621",
    "API Gravity": "40",
    "Gas-to-Oil-Ratio": "338.5125293",
    "Water-to-Oil-Ratio": "1.800402381",
    "Steam-to-Oil-Ratio": "0",
    "Flaring-to-Oil-Ratio": "0.350495704"
  },
  "Grane 2006": {
    "Unique": "Grane 2006",
    "Exploration": "0",
    "Drilling": "7.825759363",
    "Production": "7.032594183",
    "Processing": "0.512985218",
    "Upgrading": "0",
    "Maintenance": "0",
    "Waste": "0",
    "Venting, Flaring, and Fugitive Emissions": "39.35418656",
    "Diluent": "0",
    "Miscellaneous": "2.992152673",
    "Transport to Refinery": "4.096939464",
    "Offsite emissions": "15.28587659",
    "Net lifecycle emissions": "77.10049406",
    "API Gravity": "23.7",
    "Gas-to-Oil-Ratio": "194.9888377",
    "Water-to-Oil-Ratio": "0.556651383",
    "Steam-to-Oil-Ratio": "0",
    "Flaring-to-Oil-Ratio": "0.682462488"
  },
  "Gudrun 2016": {
    "Unique": "Gudrun 2016",
    "Exploration": "0",
    "Drilling": "10.00817356",
    "Production": "3.235212046",
    "Processing": "9.7920848",
    "Upgrading": "0",
    "Maintenance": "0",
    "Waste": "0",
    "Venting, Flaring, and Fugitive Emissions": "55.68678171",
    "Diluent": "0",
    "Miscellaneous": "2.791405463",
    "Transport to Refinery": "3.777267428",
    "Offsite emissions": "-3.083043483",
    "Net lifecycle emissions": "82.20788152",
    "API Gravity": "30",
    "Gas-to-Oil-Ratio": "2652.673546",
    "Water-to-Oil-Ratio": "0.033565339",
    "Steam-to-Oil-Ratio": "0",
    "Flaring-to-Oil-Ratio": "1.356328873"
  },
  "Heidrun 2006": {
    "Unique": "Heidrun 2006",
    "Exploration": "0",
    "Drilling": "7.771144227",
    "Production": "4.61363665",
    "Processing": "6.445448019",
    "Upgrading": "0",
    "Maintenance": "0",
    "Waste": "0",
    "Venting, Flaring, and Fugitive Emissions": "47.48126187",
    "Diluent": "0",
    "Miscellaneous": "2.791405463",
    "Transport to Refinery": "3.777267428",
    "Offsite emissions": "-1.140912563",
    "Net lifecycle emissions": "71.73925109",
    "API Gravity": "30",
    "Gas-to-Oil-Ratio": "1428.419807",
    "Water-to-Oil-Ratio": "0.873505544",
    "Steam-to-Oil-Ratio": "0",
    "Flaring-to-Oil-Ratio": "1.217336217"
  },
  "Njord 2006": {
    "Unique": "Njord 2006",
    "Exploration": "0",
    "Drilling": "7.683742491",
    "Production": "40.50893904",
    "Processing": "36.94471656",
    "Upgrading": "0",
    "Maintenance": "0",
    "Waste": "0",
    "Venting, Flaring, and Fugitive Emissions": "125.766876",
    "Diluent": "0",
    "Miscellaneous": "2.735095456",
    "Transport to Refinery": "3.628920107",
    "Offsite emissions": "8.237242758",
    "Net lifecycle emissions": "225.5055324",
    "API Gravity": "46.6",
    "Gas-to-Oil-Ratio": "12139.03937",
    "Water-to-Oil-Ratio": "0.173987183",
    "Steam-to-Oil-Ratio": "0",
    "Flaring-to-Oil-Ratio": "3.140234918"
  },
  "Norne 2006": {
    "Unique": "Norne 2006",
    "Exploration": "0",
    "Drilling": "8.161172676",
    "Production": "10.23077432",
    "Processing": "4.864238129",
    "Upgrading": "0",
    "Maintenance": "0",
    "Waste": "0",
    "Venting, Flaring, and Fugitive Emissions": "44.97563222",
    "Diluent": "0",
    "Miscellaneous": "2.87006469",
    "Transport to Refinery": "3.870988993",
    "Offsite emissions": "-0.447136392",
    "Net lifecycle emissions": "74.52573464",
    "API Gravity": "32.7",
    "Gas-to-Oil-Ratio": "811.291883",
    "Water-to-Oil-Ratio": "1.689855837",
    "Steam-to-Oil-Ratio": "0",
    "Flaring-to-Oil-Ratio": "1.543113775"
  },
  "Troll 2006": {
    "Unique": "Troll 2006",
    "Exploration": "0",
    "Drilling": "0.357280364",
    "Production": "7.046292971",
    "Processing": "46.87558036",
    "Upgrading": "0",
    "Maintenance": "0",
    "Waste": "0",
    "Venting, Flaring, and Fugitive Emissions": "149.2954471",
    "Diluent": "0",
    "Miscellaneous": "2.826414359",
    "Transport to Refinery": "3.795052447",
    "Offsite emissions": "-23.965005",
    "Net lifecycle emissions": "186.2310626",
    "API Gravity": "35.9",
    "Gas-to-Oil-Ratio": "15786.53901",
    "Water-to-Oil-Ratio": "2.83831062",
    "Steam-to-Oil-Ratio": "0",
    "Flaring-to-Oil-Ratio": "1.467209431"
  },
  "Valhall 2006": {
    "Unique": "Valhall 2006",
    "Exploration": "0",
    "Drilling": "7.636817223",
    "Production": "1.605402062",
    "Processing": "5.673741458",
    "Upgrading": "0",
    "Maintenance": "0",
    "Waste": "0",
    "Venting, Flaring, and Fugitive Emissions": "47.0325184",
    "Diluent": "0",
    "Miscellaneous": "2.826414359",
    "Transport to Refinery": "3.795758481",
    "Offsite emissions": "-1.429514813",
    "Net lifecycle emissions": "67.14113717",
    "API Gravity": "36",
    "Gas-to-Oil-Ratio": "1073.203016",
    "Water-to-Oil-Ratio": "0.313097971",
    "Steam-to-Oil-Ratio": "0",
    "Flaring-to-Oil-Ratio": "0.947358244"
  },
  "UK Forties Blend": {
    "Unique": "UK Forties Blend",
    "Exploration": "0",
    "Drilling": "0.622870997",
    "Production": "21.56424301",
    "Processing": "0.388743445",
    "Upgrading": "0",
    "Maintenance": "0",
    "Waste": "0",
    "Venting, Flaring, and Fugitive Emissions": "24.53899548",
    "Diluent": "0",
    "Miscellaneous": "2.791405463",
    "Transport to Refinery": "3.186934032",
    "Offsite emissions": "2.992252232",
    "Net lifecycle emissions": "56.08544466",
    "API Gravity": "35",
    "Gas-to-Oil-Ratio": "269.04",
    "Water-to-Oil-Ratio": "8.7",
    "Steam-to-Oil-Ratio": "3",
    "Flaring-to-Oil-Ratio": "102.8330831"
  }
}
