{
  "Angola Girassol": {
    "Unique": "Angola Girassol",
    "Exploration": "0",
    "Drilling": "0.330563353",
    "Production": "0.384658888",
    "Processing": "4.236767563",
    "Upgrading": "0",
    "Maintenance": "0",
    "Waste": "0",
    "Venting, Flaring, and Fugitive Emissions": "47.82894046",
    "Diluent": "0",
    "Miscellaneous": "2.909283516",
    "Transport to Refinery": "5.401430988",
    "Offsite emissions": "-0.732518822",
    "Net lifecycle emissions": "60.35912594",
    "API Gravity": "32",
    "Gas-to-Oil-Ratio": "622.115",
    "Water-to-Oil-Ratio": "0.25",
    "Steam-to-Oil-Ratio": "0",
    "Flaring-to-Oil-Ratio": "32.19558038"
  },
  "Azerbaijan Azeri Light": {
    "Unique": "Azerbaijan Azeri Light",
    "Exploration": "0",
    "Drilling": "0.912880402",
    "Production": "4.160083891",
    "Processing": "5.915629473",
    "Upgrading": "0",
    "Maintenance": "0",
    "Waste": "0",
    "Venting, Flaring, and Fugitive Emissions": "49.58905392",
    "Diluent": "0",
    "Miscellaneous": "2.843918806",
    "Transport to Refinery": "6.780835884",
    "Offsite emissions": "-1.324192151",
    "Net lifecycle emissions": "68.87821023",
    "API Gravity": "35",
    "Gas-to-Oil-Ratio": "1299",
    "Water-to-Oil-Ratio": "0.720030901",
    "Steam-to-Oil-Ratio": "0",
    "Flaring-to-Oil-Ratio": "10"
  },
  "Nigeria Agbami": {
    "Unique": "Nigeria Agbami",
    "Exploration": "0",
    "Drilling": "0",
    "Production": "0",
    "Processing": "0",
    "Upgrading": "0",
    "Maintenance": "0",
    "Waste": "0",
    "Venting, Flaring, and Fugitive Emissions": "0",
    "Diluent": "0",
    "Miscellaneous": "0",
    "Transport to Refinery": "0",
    "Offsite emissions": "0",
    "Net lifecycle emissions": "0",
    "API Gravity": "47",
    "Gas-to-Oil-Ratio": "1188.938",
    "Water-to-Oil-Ratio": "0",
    "Steam-to-Oil-Ratio": "0",
    "Flaring-to-Oil-Ratio": "56"
  },
  "Canada Hibernia": {
    "Unique": "Canada Hibernia",
    "Exploration": "0",
    "Drilling": "1.694442556",
    "Production": "5.384023596",
    "Processing": "6.24532246",
    "Upgrading": "0",
    "Maintenance": "0",
    "Waste": "0",
    "Venting, Flaring, and Fugitive Emissions": "52.73113428",
    "Diluent": "0",
    "Miscellaneous": "2.843918806",
    "Transport to Refinery": "2.105714624",
    "Offsite emissions": "1.066458378",
    "Net lifecycle emissions": "72.07101471",
    "API Gravity": "33.5",
    "Gas-to-Oil-Ratio": "1353.68965",
    "Water-to-Oil-Ratio": "0.316881761",
    "Steam-to-Oil-Ratio": "0",
    "Flaring-to-Oil-Ratio": "37.05678448"
  },
  "Norway Ekofisk": {
    "Unique": "Norway Ekofisk",
    "Exploration": "0",
    "Drilling": "1.197381056",
    "Production": "1.364970413",
    "Processing": "4.689213115",
    "Upgrading": "0",
    "Maintenance": "0",
    "Waste": "0",
    "Venting, Flaring, and Fugitive Emissions": "45.77159711",
    "Diluent": "0",
    "Miscellaneous": "2.826414359",
    "Transport to Refinery": "3.234248002",
    "Offsite emissions": "-1.704232899",
    "Net lifecycle emissions": "57.37959115",
    "API Gravity": "36",
    "Gas-to-Oil-Ratio": "1089.078",
    "Water-to-Oil-Ratio": "0.261174686",
    "Steam-to-Oil-Ratio": "0",
    "Flaring-to-Oil-Ratio": "6.504541602"
  },
  "Norway Skarv": {
    "Unique": "Norway Skarv",
    "Exploration": "0",
    "Drilling": "1.491098192",
    "Production": "0",
    "Processing": "16.68515716",
    "Upgrading": "0",
    "Maintenance": "0",
    "Waste": "0",
    "Venting, Flaring, and Fugitive Emissions": "87.97164571",
    "Diluent": "0",
    "Miscellaneous": "2.791405463",
    "Transport to Refinery": "3.181187383",
    "Offsite emissions": "-6.819670551",
    "Net lifecycle emissions": "105.3008234",
    "API Gravity": "38.5",
    "Gas-to-Oil-Ratio": "5463",
    "Water-to-Oil-Ratio": "0.063681008",
    "Steam-to-Oil-Ratio": "0",
    "Flaring-to-Oil-Ratio": "90.08109974"
  },
  "Norway Oseberg": {
    "Unique": "Norway Oseberg",
    "Exploration": "0",
    "Drilling": "0.756141587",
    "Production": "31.54052379",
    "Processing": "10.73984924",
    "Upgrading": "0",
    "Maintenance": "0",
    "Waste": "0",
    "Venting, Flaring, and Fugitive Emissions": "62.19875113",
    "Diluent": "0",
    "Miscellaneous": "2.778332521",
    "Transport to Refinery": "3.743502866",
    "Offsite emissions": "67.77262127",
    "Net lifecycle emissions": "179.5297224",
    "API Gravity": "39.6",
    "Gas-to-Oil-Ratio": "3021.743969",
    "Water-to-Oil-Ratio": "0.223736903",
    "Steam-to-Oil-Ratio": "0",
    "Flaring-to-Oil-Ratio": "16.43461822"
  },
  "U.S. Bakken": {
    "Unique": "U.S. Bakken",
    "Exploration": "0",
    "Drilling": "4.21696123",
    "Production": "1.999517607",
    "Processing": "2.352563817",
    "Upgrading": "0",
    "Maintenance": "0",
    "Waste": "0",
    "Venting, Flaring, and Fugitive Emissions": "115.4354688",
    "Diluent": "0",
    "Miscellaneous": "2.804478405",
    "Transport to Refinery": "5.52533046",
    "Offsite emissions": "-1.616699384",
    "Net lifecycle emissions": "130.717621",
    "API Gravity": "41.9",
    "Gas-to-Oil-Ratio": "1273",
    "Water-to-Oil-Ratio": "0.385",
    "Steam-to-Oil-Ratio": "0",
    "Flaring-to-Oil-Ratio": "521.6374762"
  },
  "U.S. California Midway Sunset^": {
    "Unique": "U.S. California Midway Sunset^",
    "Exploration": "0",
    "Drilling": "2.190943472",
    "Production": "3.572035216",
    "Processing": "2.612054505",
    "Upgrading": "0",
    "Maintenance": "0",
    "Waste": "0",
    "Venting, Flaring, and Fugitive Emissions": "41.80449301",
    "Diluent": "0",
    "Miscellaneous": "3.00544719",
    "Transport to Refinery": "4.023809831",
    "Offsite emissions": "20.54431729",
    "Net lifecycle emissions": "77.75310051",
    "API Gravity": "19",
    "Gas-to-Oil-Ratio": "57.77498966",
    "Water-to-Oil-Ratio": "2.672429991",
    "Steam-to-Oil-Ratio": "4.292456995",
    "Flaring-to-Oil-Ratio": "16.24708535"
  },
  "U.S. California South Belridge^": {
    "Unique": "U.S. California South Belridge^",
    "Exploration": "0",
    "Drilling": "7.921023097",
    "Production": "0.385645209",
    "Processing": "3.764368084",
    "Upgrading": "0",
    "Maintenance": "0",
    "Waste": "0",
    "Venting, Flaring, and Fugitive Emissions": "46.20886468",
    "Diluent": "0",
    "Miscellaneous": "3.118672162",
    "Transport to Refinery": "5.005180033",
    "Offsite emissions": "7.109952641",
    "Net lifecycle emissions": "73.51370591",
    "API Gravity": "23.7",
    "Gas-to-Oil-Ratio": "395.8089851",
    "Water-to-Oil-Ratio": "5.226049615",
    "Steam-to-Oil-Ratio": "1.968306324",
    "Flaring-to-Oil-Ratio": "2.244120147"
  },
  "U.S. California Wilmington^": {
    "Unique": "U.S. California Wilmington^",
    "Exploration": "0",
    "Drilling": "0.890707696",
    "Production": "10.53061066",
    "Processing": "3.249027354",
    "Upgrading": "0",
    "Maintenance": "0",
    "Waste": "0",
    "Venting, Flaring, and Fugitive Emissions": "42.0331215",
    "Diluent": "0",
    "Miscellaneous": "3.061948889",
    "Transport to Refinery": "0.071971843",
    "Offsite emissions": "2.146600895",
    "Net lifecycle emissions": "61.98398883",
    "API Gravity": "19.5",
    "Gas-to-Oil-Ratio": "278.6610386",
    "Water-to-Oil-Ratio": "14.31227574",
    "Steam-to-Oil-Ratio": "0.32377839",
    "Flaring-to-Oil-Ratio": "16.24708535"
  },
  "UK Brent": {
    "Unique": "UK Brent",
    "Exploration": "0",
    "Drilling": "0.757424053",
    "Production": "0.999086446",
    "Processing": "81.76592237",
    "Upgrading": "0",
    "Maintenance": "0",
    "Waste": "0",
    "Venting, Flaring, and Fugitive Emissions": "475.9381508",
    "Diluent": "0",
    "Miscellaneous": "2.804478405",
    "Transport to Refinery": "4.153456685",
    "Offsite emissions": "-42.41552331",
    "Net lifecycle emissions": "524.0029955",
    "API Gravity": "37.5",
    "Gas-to-Oil-Ratio": "28923.26928",
    "Water-to-Oil-Ratio": "9.376088449",
    "Steam-to-Oil-Ratio": "0",
    "Flaring-to-Oil-Ratio": "1963.470581"
  },
  "Australia Kingfish*": {
    "Unique": "Australia Kingfish*",
    "Exploration": "0",
    "Drilling": "0.630406006",
    "Production": "0.652419278",
    "Processing": "3.446417689",
    "Upgrading": "0",
    "Maintenance": "0",
    "Waste": "0",
    "Venting, Flaring, and Fugitive Emissions": "51.34500847",
    "Diluent": "0",
    "Miscellaneous": "2.735095456",
    "Transport to Refinery": "6.657191369",
    "Offsite emissions": "0.910683412",
    "Net lifecycle emissions": "66.37722168",
    "API Gravity": "47",
    "Gas-to-Oil-Ratio": "363",
    "Water-to-Oil-Ratio": "0.485849057",
    "Steam-to-Oil-Ratio": "0",
    "Flaring-to-Oil-Ratio": "73.59425509"
  },
  "Cananda Terra Nova*": {
    "Unique": "Cananda Terra Nova*",
    "Exploration": "0",
    "Drilling": "1.39825897",
    "Production": "2.213734455",
    "Processing": "3.300957464",
    "Upgrading": "0",
    "Maintenance": "0",
    "Waste": "0",
    "Venting, Flaring, and Fugitive Emissions": "71.8492166",
    "Diluent": "0",
    "Miscellaneous": "2.843918806",
    "Transport to Refinery": "2.22200447",
    "Offsite emissions": "-0.094505191",
    "Net lifecycle emissions": "83.73358558",
    "API Gravity": "35",
    "Gas-to-Oil-Ratio": "984.5399863",
    "Water-to-Oil-Ratio": "0.254395008",
    "Steam-to-Oil-Ratio": "0",
    "Flaring-to-Oil-Ratio": "219.0285946"
  },
  "Norway Statfjord": {
    "Unique": "Norway Statfjord",
    "Exploration": "0",
    "Drilling": "7.738831975",
    "Production": "12.93399436",
    "Processing": "9.677531701",
    "Upgrading": "0",
    "Maintenance": "0",
    "Waste": "0",
    "Venting, Flaring, and Fugitive Emissions": "67.32379658",
    "Diluent": "0",
    "Miscellaneous": "2.791405463",
    "Transport to Refinery": "3.838268366",
    "Offsite emissions": "-1.182026022",
    "Net lifecycle emissions": "103.1218024",
    "API Gravity": "39",
    "Gas-to-Oil-Ratio": "2567.591543",
    "Water-to-Oil-Ratio": "3.706966991",
    "Steam-to-Oil-Ratio": "0",
    "Flaring-to-Oil-Ratio": "82.42174741"
  },
  "Norway Gullfaks": {
    "Unique": "Norway Gullfaks",
    "Exploration": "0",
    "Drilling": "0.489966693",
    "Production": "58.84610552",
    "Processing": "10.31632481",
    "Upgrading": "0",
    "Maintenance": "0",
    "Waste": "0",
    "Venting, Flaring, and Fugitive Emissions": "71.78534",
    "Diluent": "0",
    "Miscellaneous": "2.804478405",
    "Transport to Refinery": "3.872281564",
    "Offsite emissions": "111.1510319",
    "Net lifecycle emissions": "259.2655289",
    "API Gravity": "37.5",
    "Gas-to-Oil-Ratio": "2949.498362",
    "Water-to-Oil-Ratio": "3.777641178",
    "Steam-to-Oil-Ratio": "0",
    "Flaring-to-Oil-Ratio": "98.9274738"
  },
  "Norway Asgard": {
    "Unique": "Norway Asgard",
    "Exploration": "0",
    "Drilling": "9.28983431",
    "Production": "100.0473798",
    "Processing": "309.000545",
    "Upgrading": "0",
    "Maintenance": "0",
    "Waste": "0",
    "Venting, Flaring, and Fugitive Emissions": "831.2671917",
    "Diluent": "0",
    "Miscellaneous": "2.697931955",
    "Transport to Refinery": "3.579611636",
    "Offsite emissions": "-134.2821718",
    "Net lifecycle emissions": "1121.600323",
    "API Gravity": "50.5",
    "Gas-to-Oil-Ratio": "110142.3003",
    "Water-to-Oil-Ratio": "0.573352861",
    "Steam-to-Oil-Ratio": "0",
    "Flaring-to-Oil-Ratio": "205.0185191"
  },
  "Norway Draugen": {
    "Unique": "Norway Draugen",
    "Exploration": "0",
    "Drilling": "7.34579379",
    "Production": "2.834450695",
    "Processing": "0.923605044",
    "Upgrading": "0",
    "Maintenance": "0",
    "Waste": "0",
    "Venting, Flaring, and Fugitive Emissions": "42.08803211",
    "Diluent": "0",
    "Miscellaneous": "2.778332521",
    "Transport to Refinery": "3.707227671",
    "Offsite emissions": "-0.318194864",
    "Net lifecycle emissions": "59.35924696",
    "API Gravity": "40",
    "Gas-to-Oil-Ratio": "338.5125293",
    "Water-to-Oil-Ratio": "0.600134127",
    "Steam-to-Oil-Ratio": "0",
    "Flaring-to-Oil-Ratio": "3.50495704"
  },
  "Norway Grane": {
    "Unique": "Norway Grane",
    "Exploration": "0",
    "Drilling": "7.825759363",
    "Production": "6.361490633",
    "Processing": "0.494802787",
    "Upgrading": "0",
    "Maintenance": "0",
    "Waste": "0",
    "Venting, Flaring, and Fugitive Emissions": "40.0865507",
    "Diluent": "0",
    "Miscellaneous": "2.992152673",
    "Transport to Refinery": "4.096939464",
    "Offsite emissions": "15.24344339",
    "Net lifecycle emissions": "77.10113901",
    "API Gravity": "23.7",
    "Gas-to-Oil-Ratio": "194.9888377",
    "Water-to-Oil-Ratio": "0.185550461",
    "Steam-to-Oil-Ratio": "0",
    "Flaring-to-Oil-Ratio": "6.824624882"
  },
  "Norway Gudrun": {
    "Unique": "Norway Gudrun",
    "Exploration": "0",
    "Drilling": "10.00817356",
    "Production": "3.155862181",
    "Processing": "9.759719465",
    "Upgrading": "0",
    "Maintenance": "0",
    "Waste": "0",
    "Venting, Flaring, and Fugitive Emissions": "57.08951635",
    "Diluent": "0",
    "Miscellaneous": "2.791405463",
    "Transport to Refinery": "3.777267428",
    "Offsite emissions": "-3.065860857",
    "Net lifecycle emissions": "83.51608359",
    "API Gravity": "30",
    "Gas-to-Oil-Ratio": "2652.673546",
    "Water-to-Oil-Ratio": "0.011188446",
    "Steam-to-Oil-Ratio": "0",
    "Flaring-to-Oil-Ratio": "13.56328873"
  },
  "Norway Heidrun": {
    "Unique": "Norway Heidrun",
    "Exploration": "0",
    "Drilling": "7.771144227",
    "Production": "3.375443618",
    "Processing": "6.374093723",
    "Upgrading": "0",
    "Maintenance": "0",
    "Waste": "0",
    "Venting, Flaring, and Fugitive Emissions": "48.74024832",
    "Diluent": "0",
    "Miscellaneous": "2.791405463",
    "Transport to Refinery": "3.777267428",
    "Offsite emissions": "-1.157760283",
    "Net lifecycle emissions": "71.6718425",
    "API Gravity": "30",
    "Gas-to-Oil-Ratio": "1428.419807",
    "Water-to-Oil-Ratio": "0.291168515",
    "Steam-to-Oil-Ratio": "0",
    "Flaring-to-Oil-Ratio": "12.17336217"
  },
  "Norway Njord": {
    "Unique": "Norway Njord",
    "Exploration": "0",
    "Drilling": "7.683742491",
    "Production": "40.20850292",
    "Processing": "36.86593845",
    "Upgrading": "0",
    "Maintenance": "0",
    "Waste": "0",
    "Venting, Flaring, and Fugitive Emissions": "129.1767985",
    "Diluent": "0",
    "Miscellaneous": "2.735095456",
    "Transport to Refinery": "3.628920107",
    "Offsite emissions": "8.189322536",
    "Net lifecycle emissions": "228.4883205",
    "API Gravity": "46.6",
    "Gas-to-Oil-Ratio": "12139.03937",
    "Water-to-Oil-Ratio": "0.057995728",
    "Steam-to-Oil-Ratio": "0",
    "Flaring-to-Oil-Ratio": "31.40234918"
  },
  "Norway Norne": {
    "Unique": "Norway Norne",
    "Exploration": "0",
    "Drilling": "8.161172676",
    "Production": "3.513234248",
    "Processing": "4.844226871",
    "Upgrading": "0",
    "Maintenance": "0",
    "Waste": "0",
    "Venting, Flaring, and Fugitive Emissions": "46.63139417",
    "Diluent": "0",
    "Miscellaneous": "2.87006469",
    "Transport to Refinery": "3.870988993",
    "Offsite emissions": "-0.571723762",
    "Net lifecycle emissions": "69.31935789",
    "API Gravity": "32.7",
    "Gas-to-Oil-Ratio": "811.291883",
    "Water-to-Oil-Ratio": "0.563285279",
    "Steam-to-Oil-Ratio": "0",
    "Flaring-to-Oil-Ratio": "15.43113775"
  },
  "Norway Troll": {
    "Unique": "Norway Troll",
    "Exploration": "0",
    "Drilling": "0.357280364",
    "Production": "4.097410156",
    "Processing": "46.90898212",
    "Upgrading": "0",
    "Maintenance": "0",
    "Waste": "0",
    "Venting, Flaring, and Fugitive Emissions": "150.8672005",
    "Diluent": "0",
    "Miscellaneous": "2.826414359",
    "Transport to Refinery": "3.795052447",
    "Offsite emissions": "-24.00676503",
    "Net lifecycle emissions": "184.8455749",
    "API Gravity": "35.9",
    "Gas-to-Oil-Ratio": "15786.53901",
    "Water-to-Oil-Ratio": "0.94610354",
    "Steam-to-Oil-Ratio": "0",
    "Flaring-to-Oil-Ratio": "14.67209431"
  },
  "Norway Valhall": {
    "Unique": "Norway Valhall",
    "Exploration": "0",
    "Drilling": "7.636817223",
    "Production": "1.289010709",
    "Processing": "5.6476672",
    "Upgrading": "0",
    "Maintenance": "0",
    "Waste": "0",
    "Venting, Flaring, and Fugitive Emissions": "48.05366448",
    "Diluent": "0",
    "Miscellaneous": "2.826414359",
    "Transport to Refinery": "3.795758481",
    "Offsite emissions": "-1.422666258",
    "Net lifecycle emissions": "67.8266662",
    "API Gravity": "36",
    "Gas-to-Oil-Ratio": "1073.203016",
    "Water-to-Oil-Ratio": "0.10436599",
    "Steam-to-Oil-Ratio": "0",
    "Flaring-to-Oil-Ratio": "9.47358244"
  },
  "UK Forties Blend^": {
    "Unique": "UK Forties Blend^",
    "Exploration": "0",
    "Drilling": "0.622870997",
    "Production": "21.56424301",
    "Processing": "0.388743445",
    "Upgrading": "0",
    "Maintenance": "0",
    "Waste": "0",
    "Venting, Flaring, and Fugitive Emissions": "24.53899548",
    "Diluent": "0",
    "Miscellaneous": "2.791405463",
    "Transport to Refinery": "3.186934032",
    "Offsite emissions": "2.992252232",
    "Net lifecycle emissions": "56.08544466",
    "API Gravity": "35",
    "Gas-to-Oil-Ratio": "269.04",
    "Water-to-Oil-Ratio": "8.7",
    "Steam-to-Oil-Ratio": "3",
    "Flaring-to-Oil-Ratio": "102.8330831"
  }
}
