{
  "Angola Girassol": {
    "Unique": "Angola Girassol",
    "Exploration": "0",
    "Drilling": "0.330563353",
    "Production": "0.516937747",
    "Processing": "4.152481077",
    "Upgrading": "0",
    "Maintenance": "0",
    "Waste": "0",
    "Venting, Flaring, and Fugitive Emissions": "51.7543126",
    "Diluent": "0",
    "Miscellaneous": "2.909283516",
    "Transport to Refinery": "5.401430988",
    "Offsite emissions": "-0.677172296",
    "Net lifecycle emissions": "64.38783698",
    "API Gravity": "32",
    "Gas-to-Oil-Ratio": "625.8975",
    "Water-to-Oil-Ratio": "0.375",
    "Steam-to-Oil-Ratio": "0",
    "Flaring-to-Oil-Ratio": "64.39116076"
  },
  "Azerbaijan Azeri Light": {
    "Unique": "Azerbaijan Azeri Light",
    "Exploration": "0",
    "Drilling": "0.912880402",
    "Production": "5.43996122",
    "Processing": "5.890024233",
    "Upgrading": "0",
    "Maintenance": "0",
    "Waste": "0",
    "Venting, Flaring, and Fugitive Emissions": "50.78670726",
    "Diluent": "0",
    "Miscellaneous": "2.843918806",
    "Transport to Refinery": "6.780835884",
    "Offsite emissions": "-1.266361753",
    "Net lifecycle emissions": "71.38796605",
    "API Gravity": "35",
    "Gas-to-Oil-Ratio": "1299",
    "Water-to-Oil-Ratio": "1.080046351",
    "Steam-to-Oil-Ratio": "0",
    "Flaring-to-Oil-Ratio": "20"
  },
  "Nigeria Agbami": {
    "Unique": "Nigeria Agbami",
    "Exploration": "0",
    "Drilling": "1.172466674",
    "Production": "2.874916911",
    "Processing": "5.660487654",
    "Upgrading": "0",
    "Maintenance": "0",
    "Waste": "0",
    "Venting, Flaring, and Fugitive Emissions": "61.35032751",
    "Diluent": "0",
    "Miscellaneous": "2.729132766",
    "Transport to Refinery": "4.332724347",
    "Offsite emissions": "-0.06412581",
    "Net lifecycle emissions": "78.05593005",
    "API Gravity": "47",
    "Gas-to-Oil-Ratio": "1188.938",
    "Water-to-Oil-Ratio": "0",
    "Steam-to-Oil-Ratio": "0",
    "Flaring-to-Oil-Ratio": "112"
  },
  "Canada Hibernia": {
    "Unique": "Canada Hibernia",
    "Exploration": "0",
    "Drilling": "1.694442556",
    "Production": "10.20547825",
    "Processing": "9.4392238",
    "Upgrading": "0",
    "Maintenance": "0",
    "Waste": "0",
    "Venting, Flaring, and Fugitive Emissions": "72.33399131",
    "Diluent": "0",
    "Miscellaneous": "2.843918806",
    "Transport to Refinery": "2.105714624",
    "Offsite emissions": "1.418394014",
    "Net lifecycle emissions": "100.0411634",
    "API Gravity": "33.5",
    "Gas-to-Oil-Ratio": "2589.778185",
    "Water-to-Oil-Ratio": "0.876135504",
    "Steam-to-Oil-Ratio": "0",
    "Flaring-to-Oil-Ratio": "129.7269082"
  },
  "Norway Ekofisk": {
    "Unique": "Norway Ekofisk",
    "Exploration": "0",
    "Drilling": "1.197381056",
    "Production": "1.476437494",
    "Processing": "5.381723151",
    "Upgrading": "0",
    "Maintenance": "0",
    "Waste": "0",
    "Venting, Flaring, and Fugitive Emissions": "51.82193769",
    "Diluent": "0",
    "Miscellaneous": "2.826414359",
    "Transport to Refinery": "3.234248002",
    "Offsite emissions": "-1.970653522",
    "Net lifecycle emissions": "63.96748823",
    "API Gravity": "36",
    "Gas-to-Oil-Ratio": "1507.762",
    "Water-to-Oil-Ratio": "0.00953516",
    "Steam-to-Oil-Ratio": "0",
    "Flaring-to-Oil-Ratio": "37"
  },
  "Norway Skarv": {
    "Unique": "Norway Skarv",
    "Exploration": "0",
    "Drilling": "1.491098192",
    "Production": "0",
    "Processing": "16.44943015",
    "Upgrading": "0",
    "Maintenance": "0",
    "Waste": "0",
    "Venting, Flaring, and Fugitive Emissions": "98.70994817",
    "Diluent": "0",
    "Miscellaneous": "2.791405463",
    "Transport to Refinery": "3.181187383",
    "Offsite emissions": "-6.695716305",
    "Net lifecycle emissions": "115.9273531",
    "API Gravity": "38.5",
    "Gas-to-Oil-Ratio": "5463",
    "Water-to-Oil-Ratio": "0.095521513",
    "Steam-to-Oil-Ratio": "0",
    "Flaring-to-Oil-Ratio": "180.1621995"
  },
  "Norway Oseberg": {
    "Unique": "Norway Oseberg",
    "Exploration": "0",
    "Drilling": "0.756141587",
    "Production": "74.93030251",
    "Processing": "15.79622604",
    "Upgrading": "0",
    "Maintenance": "0",
    "Waste": "0",
    "Venting, Flaring, and Fugitive Emissions": "84.10535212",
    "Diluent": "0",
    "Miscellaneous": "2.778332521",
    "Transport to Refinery": "3.743502866",
    "Offsite emissions": "188.0194396",
    "Net lifecycle emissions": "370.1292973",
    "API Gravity": "39.6",
    "Gas-to-Oil-Ratio": "4984.30781",
    "Water-to-Oil-Ratio": "0.727960561",
    "Steam-to-Oil-Ratio": "0",
    "Flaring-to-Oil-Ratio": "84.44870196"
  },
  "U.S. Bakken": {
    "Unique": "U.S. Bakken",
    "Exploration": "0",
    "Drilling": "4.21696123",
    "Production": "2.340941372",
    "Processing": "1.523238929",
    "Upgrading": "0",
    "Maintenance": "0",
    "Waste": "0",
    "Venting, Flaring, and Fugitive Emissions": "185.2338724",
    "Diluent": "0",
    "Miscellaneous": "2.804478405",
    "Transport to Refinery": "5.52533046",
    "Offsite emissions": "-0.182537296",
    "Net lifecycle emissions": "201.4622855",
    "API Gravity": "41.9",
    "Gas-to-Oil-Ratio": "1273",
    "Water-to-Oil-Ratio": "0.5775",
    "Steam-to-Oil-Ratio": "0",
    "Flaring-to-Oil-Ratio": "1043.274952"
  },
  "U.S. California Midway Sunset": {
    "Unique": "U.S. California Midway Sunset",
    "Exploration": "0",
    "Drilling": "2.190943472",
    "Production": "2.603524591",
    "Processing": "2.705259393",
    "Upgrading": "0",
    "Maintenance": "0",
    "Waste": "0",
    "Venting, Flaring, and Fugitive Emissions": "42.89152404",
    "Diluent": "0",
    "Miscellaneous": "3.00544719",
    "Transport to Refinery": "4.023809831",
    "Offsite emissions": "6.342238943",
    "Net lifecycle emissions": "63.76274746",
    "API Gravity": "19",
    "Gas-to-Oil-Ratio": "109.7007442",
    "Water-to-Oil-Ratio": "1.682860038",
    "Steam-to-Oil-Ratio": "1.287367792",
    "Flaring-to-Oil-Ratio": "32.4941707"
  },
  "U.S. California South Belridge": {
    "Unique": "U.S. California South Belridge",
    "Exploration": "0",
    "Drilling": "7.921023097",
    "Production": "0.66114087",
    "Processing": "3.646733427",
    "Upgrading": "0",
    "Maintenance": "0",
    "Waste": "0",
    "Venting, Flaring, and Fugitive Emissions": "47.8585252",
    "Diluent": "0",
    "Miscellaneous": "3.118672162",
    "Transport to Refinery": "5.005180033",
    "Offsite emissions": "15.90019547",
    "Net lifecycle emissions": "84.11147026",
    "API Gravity": "23.7",
    "Gas-to-Oil-Ratio": "356.0577454",
    "Water-to-Oil-Ratio": "10.20563507",
    "Steam-to-Oil-Ratio": "3.571757128",
    "Flaring-to-Oil-Ratio": "4.488240293"
  },
  "U.S. California Wilmington": {
    "Unique": "U.S. California Wilmington",
    "Exploration": "0",
    "Drilling": "0.890707696",
    "Production": "5.207529025",
    "Processing": "2.890255278",
    "Upgrading": "0",
    "Maintenance": "0",
    "Waste": "0",
    "Venting, Flaring, and Fugitive Emissions": "42.54578306",
    "Diluent": "0",
    "Miscellaneous": "3.061948889",
    "Transport to Refinery": "0.071971843",
    "Offsite emissions": "0.651054774",
    "Net lifecycle emissions": "55.31925056",
    "API Gravity": "19.5",
    "Gas-to-Oil-Ratio": "160.1301845",
    "Water-to-Oil-Ratio": "5.472580644",
    "Steam-to-Oil-Ratio": "0.004555679",
    "Flaring-to-Oil-Ratio": "32.4941707"
  },
  "Brent 1976": {
    "Unique": "Brent 1976",
    "Exploration": "0",
    "Drilling": "0.757424053",
    "Production": "0",
    "Processing": "2.596404165",
    "Upgrading": "0",
    "Maintenance": "0",
    "Waste": "0",
    "Venting, Flaring, and Fugitive Emissions": "534.8503021",
    "Diluent": "0",
    "Miscellaneous": "2.804478405",
    "Transport to Refinery": "4.153456685",
    "Offsite emissions": "0.717167851",
    "Net lifecycle emissions": "545.8792333",
    "API Gravity": "37.5",
    "Gas-to-Oil-Ratio": "3946.941162",
    "Water-to-Oil-Ratio": "0",
    "Steam-to-Oil-Ratio": "0",
    "Flaring-to-Oil-Ratio": "3926.941162"
  },
  "Kingfish 1976": {
    "Unique": "Kingfish 1976",
    "Exploration": "0",
    "Drilling": "0.630406006",
    "Production": "0.51198127",
    "Processing": "3.218345619",
    "Upgrading": "0",
    "Maintenance": "0",
    "Waste": "0",
    "Venting, Flaring, and Fugitive Emissions": "59.90814586",
    "Diluent": "0",
    "Miscellaneous": "2.735095456",
    "Transport to Refinery": "6.657191369",
    "Offsite emissions": "0.856880866",
    "Net lifecycle emissions": "74.51804644",
    "API Gravity": "47",
    "Gas-to-Oil-Ratio": "363",
    "Water-to-Oil-Ratio": "0.307783019",
    "Steam-to-Oil-Ratio": "0",
    "Flaring-to-Oil-Ratio": "147.1885102"
  },
  "Terra Nova 2015": {
    "Unique": "Terra Nova 2015",
    "Exploration": "0",
    "Drilling": "1.39825897",
    "Production": "13.08895327",
    "Processing": "5.727242976",
    "Upgrading": "0",
    "Maintenance": "0",
    "Waste": "0",
    "Venting, Flaring, and Fugitive Emissions": "95.83117009",
    "Diluent": "0",
    "Miscellaneous": "2.843918806",
    "Transport to Refinery": "2.22200447",
    "Offsite emissions": "-0.797452686",
    "Net lifecycle emissions": "120.3140959",
    "API Gravity": "35",
    "Gas-to-Oil-Ratio": "3650.653443",
    "Water-to-Oil-Ratio": "1.700101042",
    "Steam-to-Oil-Ratio": "0",
    "Flaring-to-Oil-Ratio": "313.7637997"
  },
  "Statfjord 2015": {
    "Unique": "Statfjord 2015",
    "Exploration": "0",
    "Drilling": "7.738831975",
    "Production": "1.470801514",
    "Processing": "31.45017583",
    "Upgrading": "0",
    "Maintenance": "0",
    "Waste": "0",
    "Venting, Flaring, and Fugitive Emissions": "144.0706764",
    "Diluent": "0",
    "Miscellaneous": "2.791405463",
    "Transport to Refinery": "3.838268366",
    "Offsite emissions": "-14.49914261",
    "Net lifecycle emissions": "176.8610169",
    "API Gravity": "39",
    "Gas-to-Oil-Ratio": "9896.484782",
    "Water-to-Oil-Ratio": "14.51932756",
    "Steam-to-Oil-Ratio": "0",
    "Flaring-to-Oil-Ratio": "289.3712716"
  },
  "Gullfaks 2015": {
    "Unique": "Gullfaks 2015",
    "Exploration": "0",
    "Drilling": "0.489966693",
    "Production": "65.95765826",
    "Processing": "10.05635383",
    "Upgrading": "0",
    "Maintenance": "0",
    "Waste": "0",
    "Venting, Flaring, and Fugitive Emissions": "83.5784489",
    "Diluent": "0",
    "Miscellaneous": "2.804478405",
    "Transport to Refinery": "3.872281564",
    "Offsite emissions": "113.1591674",
    "Net lifecycle emissions": "279.918355",
    "API Gravity": "37.5",
    "Gas-to-Oil-Ratio": "2949.498362",
    "Water-to-Oil-Ratio": "5.666461767",
    "Steam-to-Oil-Ratio": "0",
    "Flaring-to-Oil-Ratio": "197.8549476"
  },
  "Asgard 2016": {
    "Unique": "Asgard 2016",
    "Exploration": "0",
    "Drilling": "9.28983431",
    "Production": "100.4721711",
    "Processing": "308.4333434",
    "Upgrading": "0",
    "Maintenance": "0",
    "Waste": "0",
    "Venting, Flaring, and Fugitive Emissions": "855.6672834",
    "Diluent": "0",
    "Miscellaneous": "2.697931955",
    "Transport to Refinery": "3.579611636",
    "Offsite emissions": "-134.0169144",
    "Net lifecycle emissions": "1146.123261",
    "API Gravity": "50.5",
    "Gas-to-Oil-Ratio": "110142.3003",
    "Water-to-Oil-Ratio": "0.860029292",
    "Steam-to-Oil-Ratio": "0",
    "Flaring-to-Oil-Ratio": "410.0370383"
  },
  "Draugen 2016": {
    "Unique": "Draugen 2016",
    "Exploration": "0",
    "Drilling": "7.34579379",
    "Production": "11.25567094",
    "Processing": "0.828451123",
    "Upgrading": "0",
    "Maintenance": "0",
    "Waste": "0",
    "Venting, Flaring, and Fugitive Emissions": "46.12135409",
    "Diluent": "0",
    "Miscellaneous": "2.778332521",
    "Transport to Refinery": "3.707227671",
    "Offsite emissions": "-0.108931592",
    "Net lifecycle emissions": "71.92789854",
    "API Gravity": "40",
    "Gas-to-Oil-Ratio": "336.1649884",
    "Water-to-Oil-Ratio": "5.463845489",
    "Steam-to-Oil-Ratio": "0",
    "Flaring-to-Oil-Ratio": "36.74416981"
  },
  "Grane 2016": {
    "Unique": "Grane 2016",
    "Exploration": "0",
    "Drilling": "7.825759363",
    "Production": "14.95141221",
    "Processing": "10.3503831",
    "Upgrading": "0",
    "Maintenance": "0",
    "Waste": "0",
    "Venting, Flaring, and Fugitive Emissions": "60.12340859",
    "Diluent": "0",
    "Miscellaneous": "2.992152673",
    "Transport to Refinery": "4.096939464",
    "Offsite emissions": "20.84872541",
    "Net lifecycle emissions": "121.1887808",
    "API Gravity": "23.7",
    "Gas-to-Oil-Ratio": "2817.056384",
    "Water-to-Oil-Ratio": "0.945914131",
    "Steam-to-Oil-Ratio": "0",
    "Flaring-to-Oil-Ratio": "20.63346739"
  },
  "Gudrun 2016": {
    "Unique": "Gudrun 2016",
    "Exploration": "0",
    "Drilling": "10.00817356",
    "Production": "3.18909848",
    "Processing": "9.720986994",
    "Upgrading": "0",
    "Maintenance": "0",
    "Waste": "0",
    "Venting, Flaring, and Fugitive Emissions": "58.6481104",
    "Diluent": "0",
    "Miscellaneous": "2.791405463",
    "Transport to Refinery": "3.777267428",
    "Offsite emissions": "-3.044265572",
    "Net lifecycle emissions": "85.09077676",
    "API Gravity": "30",
    "Gas-to-Oil-Ratio": "2652.673546",
    "Water-to-Oil-Ratio": "0.01678267",
    "Steam-to-Oil-Ratio": "0",
    "Flaring-to-Oil-Ratio": "27.12657746"
  },
  "Heidrun 2016": {
    "Unique": "Heidrun 2016",
    "Exploration": "0",
    "Drilling": "7.771144227",
    "Production": "8.673492128",
    "Processing": "11.81522219",
    "Upgrading": "0",
    "Maintenance": "0",
    "Waste": "0",
    "Venting, Flaring, and Fugitive Emissions": "66.92375189",
    "Diluent": "0",
    "Miscellaneous": "2.791405463",
    "Transport to Refinery": "3.777267428",
    "Offsite emissions": "-2.252411453",
    "Net lifecycle emissions": "99.49987188",
    "API Gravity": "30",
    "Gas-to-Oil-Ratio": "3459.5521",
    "Water-to-Oil-Ratio": "1.077938269",
    "Steam-to-Oil-Ratio": "0",
    "Flaring-to-Oil-Ratio": "50.51902653"
  },
  "Njord 2016": {
    "Unique": "Njord 2016",
    "Exploration": "0",
    "Drilling": "7.683742491",
    "Production": "30.74861401",
    "Processing": "68.19969642",
    "Upgrading": "0",
    "Maintenance": "0",
    "Waste": "0",
    "Venting, Flaring, and Fugitive Emissions": "205.5313173",
    "Diluent": "0",
    "Miscellaneous": "2.735095456",
    "Transport to Refinery": "3.628920107",
    "Offsite emissions": "-22.72168515",
    "Net lifecycle emissions": "295.8057006",
    "API Gravity": "46.6",
    "Gas-to-Oil-Ratio": "22560.92593",
    "Water-to-Oil-Ratio": "0.146210885",
    "Steam-to-Oil-Ratio": "0",
    "Flaring-to-Oil-Ratio": "43.22428897"
  },
  "Norne 2016": {
    "Unique": "Norne 2016",
    "Exploration": "0",
    "Drilling": "8.161172676",
    "Production": "20.14483209",
    "Processing": "8.561441239",
    "Upgrading": "0",
    "Maintenance": "0",
    "Waste": "0",
    "Venting, Flaring, and Fugitive Emissions": "72.50719541",
    "Diluent": "0",
    "Miscellaneous": "2.87006469",
    "Transport to Refinery": "3.870988993",
    "Offsite emissions": "-2.465411287",
    "Net lifecycle emissions": "113.6502838",
    "API Gravity": "32.7",
    "Gas-to-Oil-Ratio": "2198.142503",
    "Water-to-Oil-Ratio": "10.22695013",
    "Steam-to-Oil-Ratio": "0",
    "Flaring-to-Oil-Ratio": "147.7018835"
  },
  "Troll 2016": {
    "Unique": "Troll 2016",
    "Exploration": "0",
    "Drilling": "0.357280364",
    "Production": "8.111248662",
    "Processing": "74.16337691",
    "Upgrading": "0",
    "Maintenance": "0",
    "Waste": "0",
    "Venting, Flaring, and Fugitive Emissions": "218.9928025",
    "Diluent": "0",
    "Miscellaneous": "2.826414359",
    "Transport to Refinery": "3.795052447",
    "Offsite emissions": "-37.57436757",
    "Net lifecycle emissions": "270.6718077",
    "API Gravity": "35.9",
    "Gas-to-Oil-Ratio": "25506.42391",
    "Water-to-Oil-Ratio": "1.751108054",
    "Steam-to-Oil-Ratio": "0",
    "Flaring-to-Oil-Ratio": "16.67718237"
  },
  "Valhall 2015": {
    "Unique": "Valhall 2015",
    "Exploration": "0",
    "Drilling": "7.636817223",
    "Production": "1.298326901",
    "Processing": "5.466011711",
    "Upgrading": "0",
    "Maintenance": "0",
    "Waste": "0",
    "Venting, Flaring, and Fugitive Emissions": "49.51187584",
    "Diluent": "0",
    "Miscellaneous": "2.826414359",
    "Transport to Refinery": "3.795758481",
    "Offsite emissions": "-1.313179838",
    "Net lifecycle emissions": "69.22202468",
    "API Gravity": "36",
    "Gas-to-Oil-Ratio": "1020.005467",
    "Water-to-Oil-Ratio": "0.14655157",
    "Steam-to-Oil-Ratio": "0",
    "Flaring-to-Oil-Ratio": "23.86573259"
  },
  "UK Forties Blend": {
    "Unique": "UK Forties Blend",
    "Exploration": "0",
    "Drilling": "0.622870997",
    "Production": "21.56424301",
    "Processing": "0.388743445",
    "Upgrading": "0",
    "Maintenance": "0",
    "Waste": "0",
    "Venting, Flaring, and Fugitive Emissions": "24.53899548",
    "Diluent": "0",
    "Miscellaneous": "2.791405463",
    "Transport to Refinery": "3.186934032",
    "Offsite emissions": "2.992252232",
    "Net lifecycle emissions": "56.08544466",
    "API Gravity": "35",
    "Gas-to-Oil-Ratio": "269.04",
    "Water-to-Oil-Ratio": "8.7",
    "Steam-to-Oil-Ratio": "3",
    "Flaring-to-Oil-Ratio": "102.8330831"
  }
}
